fastapi_keycloak/__init__.py
fastapi_keycloak/api.py
fastapi_keycloak/exceptions.py
fastapi_keycloak/model.py
fastapi_keycloak-1.1.1.dist-info/licenses/LICENSE
fastapi_keycloak-1.1.1.dist-info/METADATA
fastapi_keycloak-1.1.1.dist-info/WHEEL
fastapi_keycloak-1.1.1.dist-info/top_level.txt
fastapi_keycloak-1.1.1.dist-info/RECORD
