Metadata-Version: 2.4
Name: fastapi_keycloak
Version: 1.1.1
Summary: Keycloak API Client for integrating authentication and authorization with FastAPI
Author-email: Jonas Scholl <jonas@code-specialist.com>, Yannic Schröer <yannic@code-specialist.com>, Alex Barceló <alex@betarho.net>
Maintainer-email: Alex Barceló <alex@betarho.net>
Project-URL: documentation, https://fastapi-keycloak.code-specialist.com/
Project-URL: repository, https://github.com/fastapi-keycloak/fastapi-keycloak
Project-URL: issues, https://github.com/fastapi-keycloak/fastapi-keycloak/issues
Keywords: Keycloak,FastAPI,Authentication,Authorization
Classifier: Development Status :: 3 - Alpha
Classifier: Intended Audience :: Developers
Classifier: Topic :: Internet :: WWW/HTTP :: Session
Classifier: Topic :: Internet :: WWW/HTTP :: WSGI
Classifier: Topic :: Software Development :: Libraries :: Application Frameworks
Classifier: Topic :: Software Development :: Libraries :: Python Modules
Classifier: Framework :: FastAPI
Classifier: License :: OSI Approved :: Apache Software License
Classifier: Programming Language :: Python :: 3.9
Classifier: Programming Language :: Python :: 3.10
Classifier: Programming Language :: Python :: 3.11
Classifier: Programming Language :: Python :: 3.12
Requires-Python: >=3.9
License-File: LICENSE
Requires-Dist: anyio>=3.4.0
Requires-Dist: asgiref>=3.4.1
Requires-Dist: certifi>=2023.7.22
Requires-Dist: charset-normalizer>=2.0.9
Requires-Dist: click>=8.0.3
Requires-Dist: ecdsa>=0.17.0
Requires-Dist: fastapi>=0.70.1
Requires-Dist: h11>=0.12.0
Requires-Dist: idna>=3.3
Requires-Dist: pyasn1>=0.4.8
Requires-Dist: pydantic>=1.5a1
Requires-Dist: python-jose>=3.4.0
Requires-Dist: requests>=2.31.0
Requires-Dist: rsa>=4.8
Requires-Dist: six>=1.16.0
Requires-Dist: sniffio>=1.2.0
Requires-Dist: starlette>=0.36.2
Requires-Dist: typing_extensions>=4.0.1
Requires-Dist: urllib3>=1.26.17
Requires-Dist: uvicorn>=0.16.0
Requires-Dist: itsdangerous>=2.0.1
Provides-Extra: dev
Requires-Dist: pytest>=8.3.4; extra == "dev"
Requires-Dist: pytest-cov>=6.0.0; extra == "dev"
Dynamic: license-file
